notify_rs-0.6.1.dist-info/METADATA
notify_rs-0.6.1.dist-info/WHEEL
notify_rs-0.6.1.dist-info/licenses/LICENSE
notify_rs.libs/libgcc_s-262c4f60.so.1
notify_rs/__init__.py
notify_rs/__init__.pyi
notify_rs/_notify_rs.cpython-314t-arm-linux-musleabihf.so
notify_rs/py.typed
notify_rs-0.6.1.dist-info/RECORD
