Metadata-Version: 2.4
Name: notify-rs
Version: 0.6.1
Classifier: License :: OSI Approved :: MIT License
Classifier: Operating System :: OS Independent
Classifier: Programming Language :: Python
Classifier: Programming Language :: Python :: 3 :: Only
Classifier: Programming Language :: Python :: 3.8
Classifier: Programming Language :: Python :: 3.9
Classifier: Programming Language :: Python :: 3.10
Classifier: Programming Language :: Python :: 3.11
Classifier: Programming Language :: Python :: 3.12
Classifier: Programming Language :: Python :: 3.13
Classifier: Programming Language :: Python :: Implementation :: CPython
Classifier: Programming Language :: Rust
License-File: LICENSE
Summary: Wrapper around notify-rust to show desktop notifications.
Keywords: 
Home-Page: https://github.com/domdfcoding/notify-rs
Author-email: Dominic Davis-Foster <dominic@davis-foster.co.uk>
Requires-Python: >=3.8
Project-URL: Homepage, https://github.com/domdfcoding/notify-rs
Project-URL: Issue Tracker, https://github.com/domdfcoding/notify-rs/issues
Project-URL: Source Code, https://github.com/domdfcoding/notify-rs
Project-URL: Documentation, https://notify-rs.readthedocs.io/en/latest
